make_time_for_yourself.py
make_time_for_yourself-0.1.1.dist-info/METADATA
make_time_for_yourself-0.1.1.dist-info/WHEEL
make_time_for_yourself-0.1.1.dist-info/entry_points.txt
make_time_for_yourself-0.1.1.dist-info/top_level.txt
make_time_for_yourself-0.1.1.dist-info/RECORD
