Metadata-Version: 2.1
Name: make_time_for_yourself
Version: 0.1.1
Summary: A simple package to generate random numbers
Home-page: https://github.com/ktakisawa/make_time_for_yourself
Author: takisawa kazuma
Author-email: ktakisawa@sciencepark.co.jp
Classifier: Programming Language :: Python :: 3
Classifier: License :: OSI Approved :: MIT License
Classifier: Operating System :: OS Independent
Requires-Python: >=3.8
